fhir_tx/__init__.py
fhir_tx/closure.py
fhir_tx/encoder.py
fhir_tx_encoder-1.1.0.dist-info/LICENSE
fhir_tx_encoder-1.1.0.dist-info/METADATA
fhir_tx_encoder-1.1.0.dist-info/WHEEL
fhir_tx_encoder-1.1.0.dist-info/top_level.txt
fhir_tx_encoder-1.1.0.dist-info/RECORD
