Metadata-Version: 2.1
Name: fhir_tx_encoder
Version: 1.1.0
Summary: Tools for encoding FHIR terminology concepts for machine learning
Author: Australian e-Health Research Centre, CSIRO
Author-email: ontoserver-support@csiro.au
License: Apache 2.0
Requires-Python: >=3.9
License-File: LICENSE
Requires-Dist: numpy ~=1.26.0
Requires-Dist: pandas ~=2.1.2
Requires-Dist: scipy ~=1.11.3
Requires-Dist: requests ~=2.31.0
Requires-Dist: scikit-learn ~=1.3.2
